glass/ACBO.py
glass/AttrList.py
glass/BO.py
glass/Block.py
glass/CSRMat.py
glass/ComputeProgram.py
glass/DictList.py
glass/EBO.py
glass/FBO.py
glass/FBOAttachment.py
glass/GLConfig.py
glass/GLInfo.py
glass/GLObject.py
glass/GPUProgram.py
glass/GlassConfig.py
glass/ImageLoader.py
glass/ImageUnits.py
glass/Increment.py
glass/Indices.py
glass/Instances.py
glass/LICENSE
glass/MetaInstancesRecorder.py
glass/RBO.py
glass/RenderHints.py
glass/SSBO.py
glass/SSUBO.py
glass/SameTypeList.py
glass/ShaderParser.py
glass/ShaderProgram.py
glass/ShaderStorageBlock.py
glass/Shaders.py
glass/TextLoader.py
glass/TextureUnits.py
glass/UBO.py
glass/Uniform.py
glass/UniformBlock.py
glass/VAO.py
glass/VBO.py
glass/Vertices.py
glass/WeakDict.py
glass/WeakList.py
glass/WeakRef.py
glass/WeakSet.py
glass/__init__.py
glass/download.py
glass/helper.py
glass/iimage2D.py
glass/image2D.py
glass/isampler2D.py
glass/isampler2DMS.py
glass/sampler2D.py
glass/sampler2DArray.py
glass/sampler2DMS.py
glass/samplerCube.py
glass/uimage2D.py
glass/usampler2D.py
glass/usampler2DMS.py
glass/utils.py
glass/CodeCompressor/CodeCompressor.py
glass/CodeCompressor/ShaderBuiltins.py
glass/CodeCompressor/ShaderSyntaxTokens.py
glass/CodeCompressor/__init__.py
glass/CodeCompressor/generate_code.py
glass/CodeCompressor/minifyc.py
glass/CodeCompressor/pcpp/__init__.py
glass/CodeCompressor/pcpp/evaluator.py
glass/CodeCompressor/pcpp/lextab.py
glass/CodeCompressor/pcpp/parser.py
glass/CodeCompressor/pcpp/parsetab.py
glass/CodeCompressor/pcpp/pcmd.py
glass/CodeCompressor/pcpp/preprocessor.py
glass/CodeCompressor/pcpp/ply/__init__.py
glass/CodeCompressor/pcpp/ply/cpp.py
glass/CodeCompressor/pcpp/ply/ctokens.py
glass/CodeCompressor/pcpp/ply/lex.py
glass/CodeCompressor/pcpp/ply/yacc.py
glass/CodeCompressor/pcpp/ply/ygen.py
glass/__pyinstaller/__init__.py
glass/__pyinstaller/hook-glass.py
glass/glsl/draw_frame.vs
glass/glsl/shadertoy_template.fs
python_glass-0.1.64.dist-info/licenses/LICENSE
python_glass-0.1.64.dist-info/METADATA
python_glass-0.1.64.dist-info/WHEEL
python_glass-0.1.64.dist-info/entry_points.txt
python_glass-0.1.64.dist-info/top_level.txt
python_glass-0.1.64.dist-info/RECORD
