Metadata-Version: 2.4
Name: python_glass
Version: 0.1.64
Summary: OpenGL wrapper for Glass-Engine
Home-page: https://github.com/Time-Coder/Glass-Engine
Author: 王炳辉 (BingHui-WANG)
Author-email: binghui.wang@foxmail.com
Classifier: Programming Language :: Python :: 3
Classifier: License :: OSI Approved :: MIT License
Classifier: Operating System :: OS Independent
Requires-Python: >=3.7
License-File: LICENSE
Requires-Dist: PyOpenGL
Requires-Dist: PyGLM
Requires-Dist: numpy
Requires-Dist: opencv-python
Requires-Dist: wget
Requires-Dist: requests
Requires-Dist: chardet
Requires-Dist: tree-sitter>=0.22.0
Requires-Dist: tree-sitter-glsl
Requires-Dist: freetype-py
Dynamic: author
Dynamic: author-email
Dynamic: classifier
Dynamic: description
Dynamic: description-content-type
Dynamic: home-page
Dynamic: license-file
Dynamic: requires-dist
Dynamic: requires-python
Dynamic: summary
